warehub/__init__.py
warehub/__main__.py
warehub/arguments.py
warehub/command.py
warehub/config.py
warehub/database.py
warehub/exceptions.py
warehub/model.py
warehub/package.py
warehub/utils.py
warehub/templates/homepage.html
warehub/templates/release.html
warehub/templates/simple.html
warehub/templates/style.css
warehub-1.1.2.dist-info/LICENSE
warehub-1.1.2.dist-info/METADATA
warehub-1.1.2.dist-info/WHEEL
warehub-1.1.2.dist-info/eager_resources.txt
warehub-1.1.2.dist-info/entry_points.txt
warehub-1.1.2.dist-info/top_level.txt
warehub-1.1.2.dist-info/RECORD
