Metadata-Version: 2.1
Name: warehub
Version: 1.1.2
Summary: A static pypi-like Python repository generator for projects that cannot be hosted on pypi
Home-page: https://github.com/Mimer29or40/warehub/
Download-URL: https://pypi.org/project/warehub/
Author: Ryan Smith
Author-email: Ryan.Smith.Dev.Things@gmail.com
Maintainer: Ryan Smith
Maintainer-email: Ryan.Smith.Dev.Things@gmail.com
License: MIT
Project-URL: Source, https://github.com/Mimer29or40/warehub/
Project-URL: Documentation, https://github.com/Mimer29or40/warehub/wiki
Project-URL: Issue Tracker, https://github.com/Mimer29or40/warehub/issues
Keywords: pypi,warehouse,twine,warehub,github,actions
Platform: any
Classifier: Development Status :: 5 - Production/Stable
Classifier: Environment :: Console
Classifier: Environment :: Other Environment
Classifier: License :: OSI Approved :: MIT License
Classifier: Natural Language :: English
Classifier: Operating System :: OS Independent
Classifier: Programming Language :: Python :: 3
Classifier: Programming Language :: Python :: 3 :: Only
Classifier: Programming Language :: Python :: 3.8
Classifier: Programming Language :: Python :: 3.9
Classifier: Programming Language :: Python :: 3.10
Classifier: Programming Language :: Python :: 3.11
Classifier: Topic :: Database
Classifier: Topic :: Internet :: WWW/HTTP
Classifier: Topic :: Internet :: WWW/HTTP :: HTTP Servers
Classifier: Topic :: Software Development :: Libraries :: Python Modules
Classifier: Topic :: Software Development :: Version Control :: Git
Classifier: Topic :: Utilities
Requires-Python: >=3.8
License-File: LICENSE
Requires-Dist: colorama (>=0.4.4)
Requires-Dist: packaging (>=21.3)
Requires-Dist: requests (>=2.27.1)
Requires-Dist: pkginfo (>=1.8.1)
Requires-Dist: rfc3986 (>=2.0.0)
Requires-Dist: trove-classifiers (>=2022.1.6)
Requires-Dist: readme-renderer (>=32.0)
Requires-Dist: cmarkgfm (>=0.7.0)
Provides-Extra: tests
Requires-Dist: tox (>=3.24.5) ; extra == 'tests'
